odoo9_addon_res_partner_affiliate-9.0.1.0.0-py2.7-nspkg.pth
odoo_addons/res_partner_affiliate/__openerp__.py
odoo_addons/res_partner_affiliate/__init__.py
odoo_addons/res_partner_affiliate/README.rst
odoo_addons/res_partner_affiliate/models/res_partner.py
odoo_addons/res_partner_affiliate/models/__init__.py
odoo_addons/res_partner_affiliate/i18n/it.po
odoo_addons/res_partner_affiliate/i18n/es.po
odoo_addons/res_partner_affiliate/i18n/sl.po
odoo_addons/res_partner_affiliate/i18n/res_partner_affiliate.pot
odoo_addons/res_partner_affiliate/i18n/nl.po
odoo_addons/res_partner_affiliate/i18n/de.po
odoo_addons/res_partner_affiliate/i18n/fr.po
odoo_addons/res_partner_affiliate/i18n/pt_BR.po
odoo_addons/res_partner_affiliate/i18n/fi.po
odoo_addons/res_partner_affiliate/views/res_partner_view.xml
odoo_addons/res_partner_affiliate/static/description/icon.png
odoo9_addon_res_partner_affiliate-9.0.1.0.0.dist-info/top_level.txt
odoo9_addon_res_partner_affiliate-9.0.1.0.0.dist-info/WHEEL
odoo9_addon_res_partner_affiliate-9.0.1.0.0.dist-info/RECORD
odoo9_addon_res_partner_affiliate-9.0.1.0.0.dist-info/metadata.json
odoo9_addon_res_partner_affiliate-9.0.1.0.0.dist-info/DESCRIPTION.rst
odoo9_addon_res_partner_affiliate-9.0.1.0.0.dist-info/METADATA
odoo9_addon_res_partner_affiliate-9.0.1.0.0.dist-info/namespace_packages.txt
